README.md
setup.py
trust_py/__init__.py
trust_py/activation.py
trust_py/dynamics.py
trust_py/results.py
trust_py/swish_analyze.py
trust_py.egg-info/PKG-INFO
trust_py.egg-info/SOURCES.txt
trust_py.egg-info/dependency_links.txt
trust_py.egg-info/top_level.txt