Metadata-Version: 2.1
Name: trust-py
Version: 0.0.1
Summary: Code for Trust Function
Home-page: https://github.com/pypa/sampleproject
Author: Trust ICML
Author-email: 
License: UNKNOWN
Platform: UNKNOWN
Classifier: Programming Language :: Python :: 3
Classifier: License :: OSI Approved :: MIT License
Classifier: Operating System :: OS Independent
Requires-Python: >=3.6
